DjangoLaunch/__init__.py
robotframework_djangolaunch-1.0.dist-info/LICENSE.txt
robotframework_djangolaunch-1.0.dist-info/METADATA
robotframework_djangolaunch-1.0.dist-info/WHEEL
robotframework_djangolaunch-1.0.dist-info/top_level.txt
robotframework_djangolaunch-1.0.dist-info/RECORD
