Metadata-Version: 2.1
Name: robotframework-djangolaunch
Version: 1.0
Summary: A Robot Framework library for starting and stopping Django.
Home-page: https://github.com/mrannanj/robotframework-djangolaunch
Author: Martti Rannanjärvi
Author-email: martti.rannanjarvi@iki.fi
License: Apache License 2.0
Keywords: robotframework django test
Classifier: Development Status :: 5 - Production/Stable
Classifier: License :: OSI Approved :: Apache Software License
Classifier: Environment :: Web Environment
Classifier: Framework :: Robot Framework
Classifier: Framework :: Django
Classifier: Programming Language :: Python :: 3
Classifier: Programming Language :: Python :: Implementation :: CPython
License-File: LICENSE.txt
Requires-Dist: Django
Requires-Dist: robotframework
